init_film-1.4.3.dist-info/licenses/LICENSE
initfilm/Init-Film_Icon_Black.ico
initfilm/Init-Film_Icon_White.ico
initfilm/__init__.py
initfilm/clearconsole.py
initfilm/cli.py
initfilm/config.py
initfilm/config_default.json
initfilm/ffmpeg_installscript.py
initfilm/ffmpeg_presets.json
initfilm/license.py
initfilm/main.py
initfilm/shortcut.py
initfilm/templates.py
initfilm/transcode.py
init_film-1.4.3.dist-info/METADATA
init_film-1.4.3.dist-info/WHEEL
init_film-1.4.3.dist-info/entry_points.txt
init_film-1.4.3.dist-info/top_level.txt
init_film-1.4.3.dist-info/RECORD
