Metadata-Version: 2.4
Name: init-film
Version: 1.4.3
Summary: Tired of manually creating folder structures for your film/video projects? Want a folder structure that dynamically changes based on the needs for your project? Then Init-Film was made for you! By filmmakers, for filmmakers ;)
Author: Andreas Delabie
Author-email: andreas.delabie@gmail.com
License-Expression: GPL-3.0-or-later
Project-URL: Repository, https://github.com/andreasdelabie/init-film
Project-URL: Documentation, https://github.com/andreasdelabie/init-film/wiki
Project-URL: Changelog, https://github.com/andreasdelabie/init-film/releases
Project-URL: Issues, https://github.com/andreasdelabie/init-film/issues
Project-URL: Donate, https://www.buymeacoffee.com/andreasdelabie
Classifier: Development Status :: 5 - Production/Stable
Classifier: Programming Language :: Python :: 3
Classifier: Operating System :: OS Independent
Classifier: Natural Language :: English
Classifier: Environment :: Console
Classifier: Intended Audience :: End Users/Desktop
Classifier: Topic :: Multimedia :: Video
Requires-Python: >=3.10
License-File: LICENSE
Requires-Dist: darkdetect>=0.8
Requires-Dist: pyperclip>=1.9
Requires-Dist: yaspin>=3.1
Requires-Dist: typer>=0.16.0
Dynamic: license-file
